qrgen-0.4.dist-info/METADATA
qrgen-0.4.dist-info/WHEEL
qrgen-0.4.dist-info/licenses/LICENCE
qrgen/__init__.py
qrgen/server.py
qrgen/templates/index.html
qrgen-0.4.dist-info/RECORD
