Metadata-Version: 2.1
Name: qrgen
Version: 0.4
Summary: A webapp to generate QR codes
Author-Email: =?utf-8?q?Yann_de_Th=C3=A9?= <ydethe@gmail.com>
Project-URL: Bug tracker, https://https://github.com//ydethe/qrgen/issues
Project-URL: Homepage, https://https://github.com//ydethe/qrgen
Project-URL: Source, https://https://github.com//ydethe/qrgen
Requires-Python: <3.13,>=3.9
Requires-Dist: rich~=13.7.1
Requires-Dist: qrcode~=7.4
Requires-Dist: flask~=3.0
Requires-Dist: waitress~=3.0
Requires-Dist: Flask-WTF~=1.2
Requires-Dist: flask-bootstrap~=3.3
Requires-Dist: pillow~=10.4
Requires-Dist: logfire[flask]~=0.52
Requires-Dist: pydantic-settings~=2.5
